setup.py
bolclient/__init__.py
bolclient/client.py
bolclient/config.py
bolclient/exceptions.py
bolclient/helpers.py
bolclient/redis.py
bolclient.egg-info/PKG-INFO
bolclient.egg-info/SOURCES.txt
bolclient.egg-info/dependency_links.txt
bolclient.egg-info/not-zip-safe
bolclient.egg-info/requires.txt
bolclient.egg-info/top_level.txt